genice_vpython/__init__.py
genice_vpython/formats/__init__.py
genice_vpython/formats/vpython.py
genice_vpython-0.4.3.dist-info/METADATA
genice_vpython-0.4.3.dist-info/WHEEL
genice_vpython-0.4.3.dist-info/entry_points.txt
genice_vpython-0.4.3.dist-info/top_level.txt
genice_vpython-0.4.3.dist-info/RECORD
