Metadata-Version: 2.1
Name: genice-vpython
Version: 0.4.3
Summary: VPYTHON format plugin for GenIce.
Home-page: https://github.com/vitroid/genice-vpython/
Author: Masakazu Matsumoto
Author-email: vitroid@gmail.com
License: MIT
Keywords: genice,VPYTHON
Platform: UNKNOWN
Classifier: Development Status :: 4 - Beta
Classifier: Intended Audience :: Developers
Classifier: Programming Language :: Python
Classifier: Programming Language :: Python :: 3.5
Requires-Dist: vpython
Requires-Dist: genice (<2.0)
Requires-Dist: countrings (>=0.1.7)
